emcli/__init__.py
emcli/__main__.py
emcli/commands/__init__.py
emcli/commands/asg.py
emcli/commands/base.py
emcli/commands/cycle.py
emcli/commands/deploy.py
emcli/commands/instance.py
emcli/commands/patch.py
emcli/commands/publish.py
emcli/commands/service.py
emcli/commands/spinner.py
emcli/commands/toggle.py
emcli/commands/user_confirmation.py
emcli/commands/verify.py
emcli/commands/patching/__init__.py
emcli/commands/patching/patch_file.py
emcli/commands/patching/patch_operation.py
emcli/commands/patching/patch_process.py
emcli/commands/patching/patch_progress.py
emcli/commands/patching/patch_states.py
emcli/commands/patching/patch_table.py
emcli/commands/patching/validate.py
emcli/commands/utils/__init__.py
emcli/commands/utils/asg_health.py
emcli/commands/utils/file_utils.py
paradino-2.0.0.dist-info/DESCRIPTION.rst
paradino-2.0.0.dist-info/METADATA
paradino-2.0.0.dist-info/RECORD
paradino-2.0.0.dist-info/WHEEL
paradino-2.0.0.dist-info/entry_points.txt
paradino-2.0.0.dist-info/metadata.json
paradino-2.0.0.dist-info/top_level.txt
